<SYNTREE>
  <ROOT>
    <UNID>1</UNID>
    <SYMB>PROG</SYMB>
    <CHILDREN>
      <ID>2</ID>
      <ID>3</ID>
      <ID>21</ID>
    </CHILDREN>
  </ROOT>
  <INNERNODES>
    <IN>
      <PARENT>1</PARENT>
      <UNID>3</UNID>
      <SYMB>GLOBVARS</SYMB>
      <CHILDREN>
        <ID>4</ID>
        <ID>6</ID>
        <ID>8</ID>
        <ID>9</ID>
      </CHILDREN>
    </IN>
    <IN>
      <PARENT>3</PARENT>
      <UNID>4</UNID>
      <SYMB>VTYP</SYMB>
      <CHILDREN>
        <ID>5</ID>
      </CHILDREN>
    </IN>
    <IN>
      <PARENT>3</PARENT>
      <UNID>6</UNID>
      <SYMB>VNAME</SYMB>
      <CHILDREN>
        <ID>7</ID>
      </CHILDREN>
    </IN>
    <IN>
      <PARENT>3</PARENT>
      <UNID>9</UNID>
      <SYMB>GLOBVARS</SYMB>
      <CHILDREN>
        <ID>10</ID>
        <ID>12</ID>
        <ID>14</ID>
        <ID>15</ID>
      </CHILDREN>
    </IN>
    <IN>
      <PARENT>9</PARENT>
      <UNID>10</UNID>
      <SYMB>VTYP</SYMB>
      <CHILDREN>
        <ID>11</ID>
      </CHILDREN>
    </IN>
    <IN>
      <PARENT>9</PARENT>
      <UNID>12</UNID>
      <SYMB>VNAME</SYMB>
      <CHILDREN>
        <ID>13</ID>
      </CHILDREN>
    </IN>
    <IN>
      <PARENT>9</PARENT>
      <UNID>15</UNID>
      <SYMB>GLOBVARS</SYMB>
      <CHILDREN>
        <ID>16</ID>
        <ID>18</ID>
        <ID>20</ID>
      </CHILDREN>
    </IN>
    <IN>
      <PARENT>15</PARENT>
      <UNID>16</UNID>
      <SYMB>VTYP</SYMB>
      <CHILDREN>
        <ID>17</ID>
      </CHILDREN>
    </IN>
    <IN>
      <PARENT>15</PARENT>
      <UNID>18</UNID>
      <SYMB>VNAME</SYMB>
      <CHILDREN>
        <ID>19</ID>
      </CHILDREN>
    </IN>
    <IN>
      <PARENT>1</PARENT>
      <UNID>21</UNID>
      <SYMB>ALGO</SYMB>
      <CHILDREN>
        <ID>22</ID>
        <ID>23</ID>
        <ID>103</ID>
      </CHILDREN>
    </IN>
    <IN>
      <PARENT>21</PARENT>
      <UNID>23</UNID>
      <SYMB>INSTRUC</SYMB>
      <CHILDREN>
        <ID>24</ID>
        <ID>33</ID>
        <ID>34</ID>
      </CHILDREN>
    </IN>
    <IN>
      <PARENT>23</PARENT>
      <UNID>24</UNID>
      <SYMB>COMMAND</SYMB>
      <CHILDREN>
        <ID>25</ID>
      </CHILDREN>
    </IN>
    <IN>
      <PARENT>24</PARENT>
      <UNID>25</UNID>
      <SYMB>ASSIGN</SYMB>
      <CHILDREN>
        <ID>26</ID>
        <ID>28</ID>
        <ID>29</ID>
      </CHILDREN>
    </IN>
    <IN>
      <PARENT>25</PARENT>
      <UNID>26</UNID>
      <SYMB>VNAME</SYMB>
      <CHILDREN>
        <ID>27</ID>
      </CHILDREN>
    </IN>
    <IN>
      <PARENT>25</PARENT>
      <UNID>29</UNID>
      <SYMB>TERM</SYMB>
      <CHILDREN>
        <ID>30</ID>
      </CHILDREN>
    </IN>
    <IN>
      <PARENT>29</PARENT>
      <UNID>30</UNID>
      <SYMB>ATOMIC</SYMB>
      <CHILDREN>
        <ID>31</ID>
      </CHILDREN>
    </IN>
    <IN>
      <PARENT>30</PARENT>
      <UNID>31</UNID>
      <SYMB>CONST</SYMB>
      <CHILDREN>
        <ID>32</ID>
      </CHILDREN>
    </IN>
    <IN>
      <PARENT>23</PARENT>
      <UNID>34</UNID>
      <SYMB>INSTRUC</SYMB>
      <CHILDREN>
        <ID>35</ID>
        <ID>44</ID>
        <ID>45</ID>
      </CHILDREN>
    </IN>
    <IN>
      <PARENT>34</PARENT>
      <UNID>35</UNID>
      <SYMB>COMMAND</SYMB>
      <CHILDREN>
        <ID>36</ID>
      </CHILDREN>
    </IN>
    <IN>
      <PARENT>35</PARENT>
      <UNID>36</UNID>
      <SYMB>ASSIGN</SYMB>
      <CHILDREN>
        <ID>37</ID>
        <ID>39</ID>
        <ID>40</ID>
      </CHILDREN>
    </IN>
    <IN>
      <PARENT>36</PARENT>
      <UNID>37</UNID>
      <SYMB>VNAME</SYMB>
      <CHILDREN>
        <ID>38</ID>
      </CHILDREN>
    </IN>
    <IN>
      <PARENT>36</PARENT>
      <UNID>40</UNID>
      <SYMB>TERM</SYMB>
      <CHILDREN>
        <ID>41</ID>
      </CHILDREN>
    </IN>
    <IN>
      <PARENT>40</PARENT>
      <UNID>41</UNID>
      <SYMB>ATOMIC</SYMB>
      <CHILDREN>
        <ID>42</ID>
      </CHILDREN>
    </IN>
    <IN>
      <PARENT>41</PARENT>
      <UNID>42</UNID>
      <SYMB>CONST</SYMB>
      <CHILDREN>
        <ID>43</ID>
      </CHILDREN>
    </IN>
    <IN>
      <PARENT>34</PARENT>
      <UNID>45</UNID>
      <SYMB>INSTRUC</SYMB>
      <CHILDREN>
        <ID>46</ID>
        <ID>84</ID>
        <ID>85</ID>
      </CHILDREN>
    </IN>
    <IN>
      <PARENT>45</PARENT>
      <UNID>46</UNID>
      <SYMB>COMMAND</SYMB>
      <CHILDREN>
        <ID>47</ID>
      </CHILDREN>
    </IN>
    <IN>
      <PARENT>46</PARENT>
      <UNID>47</UNID>
      <SYMB>BRANCH</SYMB>
      <CHILDREN>
        <ID>48</ID>
        <ID>49</ID>
        <ID>62</ID>
        <ID>63</ID>
        <ID>73</ID>
        <ID>74</ID>
      </CHILDREN>
    </IN>
    <IN>
      <PARENT>47</PARENT>
      <UNID>49</UNID>
      <SYMB>COND</SYMB>
      <CHILDREN>
        <ID>50</ID>
      </CHILDREN>
    </IN>
    <IN>
      <PARENT>49</PARENT>
      <UNID>50</UNID>
      <SYMB>SIMPLE</SYMB>
      <CHILDREN>
        <ID>51</ID>
        <ID>53</ID>
        <ID>54</ID>
        <ID>57</ID>
        <ID>58</ID>
        <ID>61</ID>
      </CHILDREN>
    </IN>
    <IN>
      <PARENT>50</PARENT>
      <UNID>51</UNID>
      <SYMB>BINOP</SYMB>
      <CHILDREN>
        <ID>52</ID>
      </CHILDREN>
    </IN>
    <IN>
      <PARENT>50</PARENT>
      <UNID>54</UNID>
      <SYMB>ATOMIC</SYMB>
      <CHILDREN>
        <ID>55</ID>
      </CHILDREN>
    </IN>
    <IN>
      <PARENT>54</PARENT>
      <UNID>55</UNID>
      <SYMB>VNAME</SYMB>
      <CHILDREN>
        <ID>56</ID>
      </CHILDREN>
    </IN>
    <IN>
      <PARENT>50</PARENT>
      <UNID>58</UNID>
      <SYMB>ATOMIC</SYMB>
      <CHILDREN>
        <ID>59</ID>
      </CHILDREN>
    </IN>
    <IN>
      <PARENT>58</PARENT>
      <UNID>59</UNID>
      <SYMB>VNAME</SYMB>
      <CHILDREN>
        <ID>60</ID>
      </CHILDREN>
    </IN>
    <IN>
      <PARENT>47</PARENT>
      <UNID>63</UNID>
      <SYMB>ALGO</SYMB>
      <CHILDREN>
        <ID>64</ID>
        <ID>65</ID>
        <ID>72</ID>
      </CHILDREN>
    </IN>
    <IN>
      <PARENT>63</PARENT>
      <UNID>65</UNID>
      <SYMB>INSTRUC</SYMB>
      <CHILDREN>
        <ID>66</ID>
        <ID>71</ID>
      </CHILDREN>
    </IN>
    <IN>
      <PARENT>65</PARENT>
      <UNID>66</UNID>
      <SYMB>COMMAND</SYMB>
      <CHILDREN>
        <ID>67</ID>
        <ID>68</ID>
      </CHILDREN>
    </IN>
    <IN>
      <PARENT>66</PARENT>
      <UNID>68</UNID>
      <SYMB>ATOMIC</SYMB>
      <CHILDREN>
        <ID>69</ID>
      </CHILDREN>
    </IN>
    <IN>
      <PARENT>68</PARENT>
      <UNID>69</UNID>
      <SYMB>CONST</SYMB>
      <CHILDREN>
        <ID>70</ID>
      </CHILDREN>
    </IN>
    <IN>
      <PARENT>47</PARENT>
      <UNID>74</UNID>
      <SYMB>ALGO</SYMB>
      <CHILDREN>
        <ID>75</ID>
        <ID>76</ID>
        <ID>83</ID>
      </CHILDREN>
    </IN>
    <IN>
      <PARENT>74</PARENT>
      <UNID>76</UNID>
      <SYMB>INSTRUC</SYMB>
      <CHILDREN>
        <ID>77</ID>
        <ID>82</ID>
      </CHILDREN>
    </IN>
    <IN>
      <PARENT>76</PARENT>
      <UNID>77</UNID>
      <SYMB>COMMAND</SYMB>
      <CHILDREN>
        <ID>78</ID>
        <ID>79</ID>
      </CHILDREN>
    </IN>
    <IN>
      <PARENT>77</PARENT>
      <UNID>79</UNID>
      <SYMB>ATOMIC</SYMB>
      <CHILDREN>
        <ID>80</ID>
      </CHILDREN>
    </IN>
    <IN>
      <PARENT>79</PARENT>
      <UNID>80</UNID>
      <SYMB>CONST</SYMB>
      <CHILDREN>
        <ID>81</ID>
      </CHILDREN>
    </IN>
    <IN>
      <PARENT>45</PARENT>
      <UNID>85</UNID>
      <SYMB>INSTRUC</SYMB>
      <CHILDREN>
        <ID>86</ID>
        <ID>95</ID>
        <ID>96</ID>
      </CHILDREN>
    </IN>
    <IN>
      <PARENT>85</PARENT>
      <UNID>86</UNID>
      <SYMB>COMMAND</SYMB>
      <CHILDREN>
        <ID>87</ID>
      </CHILDREN>
    </IN>
    <IN>
      <PARENT>86</PARENT>
      <UNID>87</UNID>
      <SYMB>ASSIGN</SYMB>
      <CHILDREN>
        <ID>88</ID>
        <ID>90</ID>
        <ID>91</ID>
      </CHILDREN>
    </IN>
    <IN>
      <PARENT>87</PARENT>
      <UNID>88</UNID>
      <SYMB>VNAME</SYMB>
      <CHILDREN>
        <ID>89</ID>
      </CHILDREN>
    </IN>
    <IN>
      <PARENT>87</PARENT>
      <UNID>91</UNID>
      <SYMB>TERM</SYMB>
      <CHILDREN>
        <ID>92</ID>
      </CHILDREN>
    </IN>
    <IN>
      <PARENT>91</PARENT>
      <UNID>92</UNID>
      <SYMB>ATOMIC</SYMB>
      <CHILDREN>
        <ID>93</ID>
      </CHILDREN>
    </IN>
    <IN>
      <PARENT>92</PARENT>
      <UNID>93</UNID>
      <SYMB>VNAME</SYMB>
      <CHILDREN>
        <ID>94</ID>
      </CHILDREN>
    </IN>
    <IN>
      <PARENT>85</PARENT>
      <UNID>96</UNID>
      <SYMB>INSTRUC</SYMB>
      <CHILDREN>
        <ID>97</ID>
        <ID>102</ID>
      </CHILDREN>
    </IN>
    <IN>
      <PARENT>96</PARENT>
      <UNID>97</UNID>
      <SYMB>COMMAND</SYMB>
      <CHILDREN>
        <ID>98</ID>
        <ID>99</ID>
      </CHILDREN>
    </IN>
    <IN>
      <PARENT>97</PARENT>
      <UNID>99</UNID>
      <SYMB>ATOMIC</SYMB>
      <CHILDREN>
        <ID>100</ID>
      </CHILDREN>
    </IN>
    <IN>
      <PARENT>99</PARENT>
      <UNID>100</UNID>
      <SYMB>VNAME</SYMB>
      <CHILDREN>
        <ID>101</ID>
      </CHILDREN>
    </IN>
  </INNERNODES>
  <LEAFNODES>
    <LEAF>
      <PARENT>1</PARENT>
      <UNID>2</UNID>
      <TERMINAL>
        <TOKEN>
            <TYPE>reserved_keyword</TYPE>
            <VALUE>main</VALUE>
        </TOKEN>
      </TERMINAL>
    </LEAF>
    <LEAF>
      <PARENT>4</PARENT>
      <UNID>5</UNID>
      <TERMINAL>
        <TOKEN>
            <TYPE>reserved_keyword</TYPE>
            <VALUE>num</VALUE>
        </TOKEN>
      </TERMINAL>
    </LEAF>
    <LEAF>
      <PARENT>6</PARENT>
      <UNID>7</UNID>
      <TERMINAL>
        <TOKEN>
            <TYPE>V</TYPE>
            <VALUE>V_a01</VALUE>
        </TOKEN>
      </TERMINAL>
    </LEAF>
    <LEAF>
      <PARENT>3</PARENT>
      <UNID>8</UNID>
      <TERMINAL>
        <TOKEN>
            <TYPE>reserved_keyword</TYPE>
            <VALUE>,</VALUE>
        </TOKEN>
      </TERMINAL>
    </LEAF>
    <LEAF>
      <PARENT>10</PARENT>
      <UNID>11</UNID>
      <TERMINAL>
        <TOKEN>
            <TYPE>reserved_keyword</TYPE>
            <VALUE>num</VALUE>
        </TOKEN>
      </TERMINAL>
    </LEAF>
    <LEAF>
      <PARENT>12</PARENT>
      <UNID>13</UNID>
      <TERMINAL>
        <TOKEN>
            <TYPE>V</TYPE>
            <VALUE>V_a02</VALUE>
        </TOKEN>
      </TERMINAL>
    </LEAF>
    <LEAF>
      <PARENT>9</PARENT>
      <UNID>14</UNID>
      <TERMINAL>
        <TOKEN>
            <TYPE>reserved_keyword</TYPE>
            <VALUE>,</VALUE>
        </TOKEN>
      </TERMINAL>
    </LEAF>
    <LEAF>
      <PARENT>16</PARENT>
      <UNID>17</UNID>
      <TERMINAL>
        <TOKEN>
            <TYPE>reserved_keyword</TYPE>
            <VALUE>num</VALUE>
        </TOKEN>
      </TERMINAL>
    </LEAF>
    <LEAF>
      <PARENT>18</PARENT>
      <UNID>19</UNID>
      <TERMINAL>
        <TOKEN>
            <TYPE>V</TYPE>
            <VALUE>V_a03</VALUE>
        </TOKEN>
      </TERMINAL>
    </LEAF>
    <LEAF>
      <PARENT>15</PARENT>
      <UNID>20</UNID>
      <TERMINAL>
        <TOKEN>
            <TYPE>reserved_keyword</TYPE>
            <VALUE>,</VALUE>
        </TOKEN>
      </TERMINAL>
    </LEAF>
    <LEAF>
      <PARENT>21</PARENT>
      <UNID>22</UNID>
      <TERMINAL>
        <TOKEN>
            <TYPE>reserved_keyword</TYPE>
            <VALUE>begin</VALUE>
        </TOKEN>
      </TERMINAL>
    </LEAF>
    <LEAF>
      <PARENT>26</PARENT>
      <UNID>27</UNID>
      <TERMINAL>
        <TOKEN>
            <TYPE>V</TYPE>
            <VALUE>V_a01</VALUE>
        </TOKEN>
      </TERMINAL>
    </LEAF>
    <LEAF>
      <PARENT>25</PARENT>
      <UNID>28</UNID>
      <TERMINAL>
        <TOKEN>
            <TYPE>reserved_keyword</TYPE>
            <VALUE>=</VALUE>
        </TOKEN>
      </TERMINAL>
    </LEAF>
    <LEAF>
      <PARENT>31</PARENT>
      <UNID>32</UNID>
      <TERMINAL>
        <TOKEN>
            <TYPE>N</TYPE>
            <VALUE>10</VALUE>
        </TOKEN>
      </TERMINAL>
    </LEAF>
    <LEAF>
      <PARENT>23</PARENT>
      <UNID>33</UNID>
      <TERMINAL>
        <TOKEN>
            <TYPE>reserved_keyword</TYPE>
            <VALUE>;</VALUE>
        </TOKEN>
      </TERMINAL>
    </LEAF>
    <LEAF>
      <PARENT>37</PARENT>
      <UNID>38</UNID>
      <TERMINAL>
        <TOKEN>
            <TYPE>V</TYPE>
            <VALUE>V_a02</VALUE>
        </TOKEN>
      </TERMINAL>
    </LEAF>
    <LEAF>
      <PARENT>36</PARENT>
      <UNID>39</UNID>
      <TERMINAL>
        <TOKEN>
            <TYPE>reserved_keyword</TYPE>
            <VALUE>=</VALUE>
        </TOKEN>
      </TERMINAL>
    </LEAF>
    <LEAF>
      <PARENT>42</PARENT>
      <UNID>43</UNID>
      <TERMINAL>
        <TOKEN>
            <TYPE>N</TYPE>
            <VALUE>20</VALUE>
        </TOKEN>
      </TERMINAL>
    </LEAF>
    <LEAF>
      <PARENT>34</PARENT>
      <UNID>44</UNID>
      <TERMINAL>
        <TOKEN>
            <TYPE>reserved_keyword</TYPE>
            <VALUE>;</VALUE>
        </TOKEN>
      </TERMINAL>
    </LEAF>
    <LEAF>
      <PARENT>47</PARENT>
      <UNID>48</UNID>
      <TERMINAL>
        <TOKEN>
            <TYPE>reserved_keyword</TYPE>
            <VALUE>if</VALUE>
        </TOKEN>
      </TERMINAL>
    </LEAF>
    <LEAF>
      <PARENT>51</PARENT>
      <UNID>52</UNID>
      <TERMINAL>
        <TOKEN>
            <TYPE>reserved_keyword</TYPE>
            <VALUE>grt</VALUE>
        </TOKEN>
      </TERMINAL>
    </LEAF>
    <LEAF>
      <PARENT>50</PARENT>
      <UNID>53</UNID>
      <TERMINAL>
        <TOKEN>
            <TYPE>reserved_keyword</TYPE>
            <VALUE>(</VALUE>
        </TOKEN>
      </TERMINAL>
    </LEAF>
    <LEAF>
      <PARENT>55</PARENT>
      <UNID>56</UNID>
      <TERMINAL>
        <TOKEN>
            <TYPE>V</TYPE>
            <VALUE>V_a02</VALUE>
        </TOKEN>
      </TERMINAL>
    </LEAF>
    <LEAF>
      <PARENT>50</PARENT>
      <UNID>57</UNID>
      <TERMINAL>
        <TOKEN>
            <TYPE>reserved_keyword</TYPE>
            <VALUE>,</VALUE>
        </TOKEN>
      </TERMINAL>
    </LEAF>
    <LEAF>
      <PARENT>59</PARENT>
      <UNID>60</UNID>
      <TERMINAL>
        <TOKEN>
            <TYPE>V</TYPE>
            <VALUE>V_a01</VALUE>
        </TOKEN>
      </TERMINAL>
    </LEAF>
    <LEAF>
      <PARENT>50</PARENT>
      <UNID>61</UNID>
      <TERMINAL>
        <TOKEN>
            <TYPE>reserved_keyword</TYPE>
            <VALUE>)</VALUE>
        </TOKEN>
      </TERMINAL>
    </LEAF>
    <LEAF>
      <PARENT>47</PARENT>
      <UNID>62</UNID>
      <TERMINAL>
        <TOKEN>
            <TYPE>reserved_keyword</TYPE>
            <VALUE>then</VALUE>
        </TOKEN>
      </TERMINAL>
    </LEAF>
    <LEAF>
      <PARENT>63</PARENT>
      <UNID>64</UNID>
      <TERMINAL>
        <TOKEN>
            <TYPE>reserved_keyword</TYPE>
            <VALUE>begin</VALUE>
        </TOKEN>
      </TERMINAL>
    </LEAF>
    <LEAF>
      <PARENT>66</PARENT>
      <UNID>67</UNID>
      <TERMINAL>
        <TOKEN>
            <TYPE>reserved_keyword</TYPE>
            <VALUE>print</VALUE>
        </TOKEN>
      </TERMINAL>
    </LEAF>
    <LEAF>
      <PARENT>69</PARENT>
      <UNID>70</UNID>
      <TERMINAL>
        <TOKEN>
            <TYPE>T</TYPE>
            <VALUE>&quot;Yes&quot;</VALUE>
        </TOKEN>
      </TERMINAL>
    </LEAF>
    <LEAF>
      <PARENT>65</PARENT>
      <UNID>71</UNID>
      <TERMINAL>
        <TOKEN>
            <TYPE>reserved_keyword</TYPE>
            <VALUE>;</VALUE>
        </TOKEN>
      </TERMINAL>
    </LEAF>
    <LEAF>
      <PARENT>63</PARENT>
      <UNID>72</UNID>
      <TERMINAL>
        <TOKEN>
            <TYPE>reserved_keyword</TYPE>
            <VALUE>end</VALUE>
        </TOKEN>
      </TERMINAL>
    </LEAF>
    <LEAF>
      <PARENT>47</PARENT>
      <UNID>73</UNID>
      <TERMINAL>
        <TOKEN>
            <TYPE>reserved_keyword</TYPE>
            <VALUE>else</VALUE>
        </TOKEN>
      </TERMINAL>
    </LEAF>
    <LEAF>
      <PARENT>74</PARENT>
      <UNID>75</UNID>
      <TERMINAL>
        <TOKEN>
            <TYPE>reserved_keyword</TYPE>
            <VALUE>begin</VALUE>
        </TOKEN>
      </TERMINAL>
    </LEAF>
    <LEAF>
      <PARENT>77</PARENT>
      <UNID>78</UNID>
      <TERMINAL>
        <TOKEN>
            <TYPE>reserved_keyword</TYPE>
            <VALUE>print</VALUE>
        </TOKEN>
      </TERMINAL>
    </LEAF>
    <LEAF>
      <PARENT>80</PARENT>
      <UNID>81</UNID>
      <TERMINAL>
        <TOKEN>
            <TYPE>T</TYPE>
            <VALUE>&quot;No&quot;</VALUE>
        </TOKEN>
      </TERMINAL>
    </LEAF>
    <LEAF>
      <PARENT>76</PARENT>
      <UNID>82</UNID>
      <TERMINAL>
        <TOKEN>
            <TYPE>reserved_keyword</TYPE>
            <VALUE>;</VALUE>
        </TOKEN>
      </TERMINAL>
    </LEAF>
    <LEAF>
      <PARENT>74</PARENT>
      <UNID>83</UNID>
      <TERMINAL>
        <TOKEN>
            <TYPE>reserved_keyword</TYPE>
            <VALUE>end</VALUE>
        </TOKEN>
      </TERMINAL>
    </LEAF>
    <LEAF>
      <PARENT>45</PARENT>
      <UNID>84</UNID>
      <TERMINAL>
        <TOKEN>
            <TYPE>reserved_keyword</TYPE>
            <VALUE>;</VALUE>
        </TOKEN>
      </TERMINAL>
    </LEAF>
    <LEAF>
      <PARENT>88</PARENT>
      <UNID>89</UNID>
      <TERMINAL>
        <TOKEN>
            <TYPE>V</TYPE>
            <VALUE>V_a03</VALUE>
        </TOKEN>
      </TERMINAL>
    </LEAF>
    <LEAF>
      <PARENT>87</PARENT>
      <UNID>90</UNID>
      <TERMINAL>
        <TOKEN>
            <TYPE>reserved_keyword</TYPE>
            <VALUE>=</VALUE>
        </TOKEN>
      </TERMINAL>
    </LEAF>
    <LEAF>
      <PARENT>93</PARENT>
      <UNID>94</UNID>
      <TERMINAL>
        <TOKEN>
            <TYPE>V</TYPE>
            <VALUE>V_a01</VALUE>
        </TOKEN>
      </TERMINAL>
    </LEAF>
    <LEAF>
      <PARENT>85</PARENT>
      <UNID>95</UNID>
      <TERMINAL>
        <TOKEN>
            <TYPE>reserved_keyword</TYPE>
            <VALUE>;</VALUE>
        </TOKEN>
      </TERMINAL>
    </LEAF>
    <LEAF>
      <PARENT>97</PARENT>
      <UNID>98</UNID>
      <TERMINAL>
        <TOKEN>
            <TYPE>reserved_keyword</TYPE>
            <VALUE>print</VALUE>
        </TOKEN>
      </TERMINAL>
    </LEAF>
    <LEAF>
      <PARENT>100</PARENT>
      <UNID>101</UNID>
      <TERMINAL>
        <TOKEN>
            <TYPE>V</TYPE>
            <VALUE>V_a03</VALUE>
        </TOKEN>
      </TERMINAL>
    </LEAF>
    <LEAF>
      <PARENT>96</PARENT>
      <UNID>102</UNID>
      <TERMINAL>
        <TOKEN>
            <TYPE>reserved_keyword</TYPE>
            <VALUE>;</VALUE>
        </TOKEN>
      </TERMINAL>
    </LEAF>
    <LEAF>
      <PARENT>21</PARENT>
      <UNID>103</UNID>
      <TERMINAL>
        <TOKEN>
            <TYPE>reserved_keyword</TYPE>
            <VALUE>end</VALUE>
        </TOKEN>
      </TERMINAL>
    </LEAF>
  </LEAFNODES>
</SYNTREE>